BiModNeuroCNN/__init__.py
BiModNeuroCNN/utils.py
BiModNeuroCNN/utils_final.py
BiModNeuroCNN/version.py
BiModNeuroCNN/data_loader/__init__.py
BiModNeuroCNN/data_loader/data_loader.py
BiModNeuroCNN/data_loader/data_utils.py
BiModNeuroCNN/data_loader/signal_processing_utils.py
BiModNeuroCNN/data_loader/utils1.py
BiModNeuroCNN/models/__init__.py
BiModNeuroCNN/models/bimodal_cnn.py
BiModNeuroCNN/models/bimodal_cnn_pooling.py
BiModNeuroCNN/models/network_utils.py
BiModNeuroCNN/results/__init__.py
BiModNeuroCNN/results/dataframe_utils.py
BiModNeuroCNN/results/metrics.py
BiModNeuroCNN/results/results.py
BiModNeuroCNN/subjects/__init__.py
BiModNeuroCNN/subjects/subjects.py
BiModNeuroCNN/subjects/subjects_utils.py
BiModNeuroCNN/training/__init__.py
BiModNeuroCNN/training/bimodal_classification.py
BiModNeuroCNN/training/bimodal_training.py
BiModNeuroCNN/training/training_utils.py
BiModNeuroCNN-0.1.0.dist-info/License.txt.txt
BiModNeuroCNN-0.1.0.dist-info/METADATA
BiModNeuroCNN-0.1.0.dist-info/WHEEL
BiModNeuroCNN-0.1.0.dist-info/top_level.txt
BiModNeuroCNN-0.1.0.dist-info/RECORD
