Metadata-Version: 2.1
Name: BiModNeuroCNN
Version: 0.1.0
Summary: Tools for bimodal training of CNNs, i.e. concurrent training with two data types
Home-page: https://github.com/cfcooney
Author: Ciaran Cooney
License: MIT License
Platform: UNKNOWN
Classifier: Intended Audience :: Developers
Classifier: Intended Audience :: Science/Research
Classifier: Topic :: Software Development :: Build Tools
Classifier: Topic :: Scientific/Engineering :: Artificial Intelligence
Classifier: Programming Language :: Python :: 3.6
Requires-Dist: braindecode (==0.4.85)
Requires-Dist: mne
Requires-Dist: numpy
Requires-Dist: pandas
Requires-Dist: scipy
Requires-Dist: matplotlib
